<?xml version="1.0"?>
<!--
 * Copyright (C) 2001 Global Retail Technology, LLC
 * <http://www.globalretailtech.com>
 *
 * This program is free software; you can redistribute it and/or
 * modify it under the terms of the GNU General Public License
 * as published by the Free Software Foundation; either version 2
 * of the License, or any later version.
 *
 * This program is distributed in the hope that it will be useful,
 * but WITHOUT ANY WARRANTY; without even the implied warranty of
 * MERCHANTABILITY or FITNESS FOR A PARTICULAR PURPOSE.  See the
 * GNU General Public License for more details.
 *
 * You should have received a copy of the GNU General Public License
 * along with this program; if not, write to the Free Software
 * Foundation, Inc., 59 Temple Place - Suite 330, Boston, MA  02111-1307, USA.
-->

<mercatordata>


<table>
  <name>employee</name>
  <columns>
    <column type="integer" unique="gen_employee">employee_id</column>
    <column type="integer">logon_no</column>
    <column type="integer">logon_pass</column>
    <column type="integer">profile</column>
    <column type="varchar(32)">fname</column>
    <column type="varchar(32)">lname</column>
    <column type="varchar(1)">mi</column>
    <column type="varchar(9)">ssn</column>
    <column type="integer">sal_grade</column>
    <column type="numeric">hourly_wage</column>
    <column type="varchar(30)">employee_key</column>
  </columns>
</table>
    

</mercatordata>
